vaxila/hello.py
vaxila-0.0.0.dist-info/METADATA
vaxila-0.0.0.dist-info/WHEEL
vaxila-0.0.0.dist-info/licenses/LICENSE
vaxila-0.0.0.dist-info/RECORD
